LICENSE
MANIFEST.in
README.md
setup.cfg
setup.py
tap_bold/__init__.py
tap_bold/schema.py
tap_bold.egg-info/PKG-INFO
tap_bold.egg-info/SOURCES.txt
tap_bold.egg-info/dependency_links.txt
tap_bold.egg-info/entry_points.txt
tap_bold.egg-info/requires.txt
tap_bold.egg-info/top_level.txt
tap_bold/schemas/subscriptions.json