Metadata-Version: 1.1
Name: tap-bold
Version: 0.4.0
Summary: Singer.io tap for extracting data from Bold Recurring Orders Subscriptions API
Home-page: http://singer.io
Author: Ori Ben Aharon
Author-email: UNKNOWN
License: agpl-3.0
Download-URL: https://github.com/oriskincare/tap-bold/archive/v0.5.0.tar.gz
Keywords: SINGER,TAP
Platform: UNKNOWN
Classifier: Development Status :: 3 - Alpha
Classifier: Intended Audience :: Developers
Classifier: Programming Language :: Python :: 3
